{
  "shapes": [
    {
      "points": [
        [
          0.6620000000000001,
          0.351056338028169
        ],
        [
          0.548,
          0.31936619718309855
        ],
        [
          0.422,
          0.31936619718309855
        ],
        [
          0.317,
          0.3415492957746479
        ],
        [
          0.377,
          0.22112676056338026
        ],
        [
          0.434,
          0.1609154929577465
        ],
        [
          0.494,
          0.12922535211267605
        ],
        [
          0.548,
          0.1609154929577465
        ],
        [
          0.6050000000000001,
          0.22112676056338026
        ],
        [
          0.659,
          0.3161971830985915
        ],
        [
          0.6620000000000001,
          0.351056338028169
        ]
      ],
      "closed": true
    },
    {
      "points": [
        [
          0.521,
          0.5316901408450704
        ],
        [
          0.5660000000000001,
          0.5095070422535212
        ],
        [
          0.611,
          0.4556338028169014
        ],
        [
          0.6230000000000001,
          0.38591549295774646
        ],
        [
          0.6080000000000001,
          0.3700704225352113
        ],
        [
          0.56,
          0.35739436619718307
        ],
        [
          0.416,
          0.35739436619718307
        ],
        [
          0.368,
          0.3700704225352113
        ],
        [
          0.353,
          0.38591549295774646
        ],
        [
          0.359,
          0.43661971830985913
        ],
        [
          0.377,
          0.47464788732394364
        ],
        [
          0.41000000000000003,
          0.5095070422535212
        ],
        [
          0.464,
          0.5348591549295775
        ],
        [
          0.521,
          0.5316901408450704
        ]
      ],
      "closed": true
    },
    {
      "points": [
        [
          0.53,
          0.5538732394366198
        ],
        [
          0.452,
          0.5538732394366198
        ],
        [
          0.362,
          0.5031690140845071
        ],
        [
          0.311,
          0.43661971830985913
        ],
        [
          0.311,
          0.3732394366197183
        ],
        [
          0.41000000000000003,
          0.33838028169014084
        ],
        [
          0.56,
          0.33838028169014084
        ],
        [
          0.668,
          0.3700704225352113
        ],
        [
          0.671,
          0.4429577464788732
        ],
        [
          0.6530000000000001,
          0.47464788732394364
        ],
        [
          0.6080000000000001,
          0.5158450704225352
        ],
        [
          0.53,
          0.5538732394366198
        ]
      ],
      "closed": true
    },
    {
      "points": [
        [
          0.5150000000000001,
          0.7725352112676057
        ],
        [
          0.527,
          0.7661971830985916
        ],
        [
          0.527,
          0.721830985915493
        ],
        [
          0.5,
          0.7123239436619719
        ],
        [
          0.5150000000000001,
          0.721830985915493
        ],
        [
          0.5150000000000001,
          0.7345070422535211
        ],
        [
          0.503,
          0.7408450704225352
        ],
        [
          0.521,
          0.7598591549295775
        ],
        [
          0.491,
          0.7725352112676057
        ],
        [
          0.5150000000000001,
          0.7725352112676057
        ]
      ],
      "closed": true
    },
    {
      "points": [
        [
          0.473,
          0.7725352112676057
        ],
        [
          0.485,
          0.7661971830985916
        ],
        [
          0.485,
          0.721830985915493
        ],
        [
          0.476,
          0.7123239436619719
        ],
        [
          0.452,
          0.7123239436619719
        ],
        [
          0.449,
          0.7725352112676057
        ],
        [
          0.473,
          0.7725352112676057
        ]
      ],
      "closed": true
    },
    {
      "points": [
        [
          0.47000000000000003,
          0.7693661971830987
        ],
        [
          0.461,
          0.7661971830985916
        ],
        [
          0.464,
          0.7440140845070423
        ],
        [
          0.47900000000000004,
          0.7535211267605634
        ],
        [
          0.47000000000000003,
          0.7693661971830987
        ]
      ],
      "closed": true
    },
    {
      "points": [
        [
          0.6920000000000001,
          0.8771126760563381
        ],
        [
          0.28400000000000003,
          0.8771126760563381
        ],
        [
          0.28099999999999997,
          0.6267605633802817
        ],
        [
          0.6920000000000001,
          0.6235915492957748
        ],
        [
          0.6920000000000001,
          0.8771126760563381
        ]
      ],
      "closed": true
    },
    {
      "points": [
        [
          0.728,
          0.86443661971831
        ],
        [
          0.7130000000000001,
          0.8612676056338029
        ],
        [
          0.71,
          0.6045774647887324
        ],
        [
          0.272,
          0.6045774647887324
        ],
        [
          0.263,
          0.6140845070422536
        ],
        [
          0.26,
          0.8580985915492959
        ],
        [
          0.20600000000000002,
          0.8327464788732395
        ],
        [
          0.185,
          0.8042253521126761
        ],
        [
          0.173,
          0.7661971830985916
        ],
        [
          0.179,
          0.7028169014084508
        ],
        [
          0.20900000000000002,
          0.6204225352112677
        ],
        [
          0.245,
          0.5570422535211268
        ],
        [
          0.32599999999999996,
          0.5031690140845071
        ],
        [
          0.45799999999999996,
          0.572887323943662
        ],
        [
          0.524,
          0.572887323943662
        ],
        [
          0.5900000000000001,
          0.5475352112676057
        ],
        [
          0.6440000000000001,
          0.5031690140845071
        ],
        [
          0.6620000000000001,
          0.5031690140845071
        ],
        [
          0.7430000000000001,
          0.5570422535211268
        ],
        [
          0.797,
          0.7028169014084508
        ],
        [
          0.797,
          0.8105633802816902
        ],
        [
          0.7700000000000001,
          0.8454225352112678
        ],
        [
          0.728,
          0.86443661971831
        ]
      ],
      "closed": true
    },
    {
      "points": [
        [
          0.8240000000000001,
          0.9404929577464789
        ],
        [
          0.158,
          0.9404929577464789
        ],
        [
          0.137,
          0.9246478873239438
        ],
        [
          0.137,
          0.9119718309859155
        ],
        [
          0.152,
          0.8961267605633804
        ],
        [
          0.28400000000000003,
          0.8897887323943663
        ],
        [
          0.6920000000000001,
          0.8897887323943663
        ],
        [
          0.8300000000000001,
          0.8961267605633804
        ],
        [
          0.8390000000000001,
          0.9246478873239438
        ],
        [
          0.8240000000000001,
          0.9404929577464789
        ]
      ],
      "closed": true
    }
  ],
  "metadata": {
    "source": "image_to_trajectory.py",
    "num_shapes": 9,
    "total_points": 97
  }
}